<?xml version="1.0" encoding="iso-8859-1"?><PHOTOLIST><COMMON><VERSION>1.0</VERSION></COMMON><PHOTO ID="PHOTO"><ENTRY><FILENAME>IMG00001.JPG</FILENAME><DATE>20170328</DATE><TIME>192010</TIME></ENTRY></PHOTO><PHOTO ID="HOUSE_SITTING"></PHOTO><PHOTO ID="OWNER"></PHOTO><PHOTO ID="FAVORITE"></PHOTO><PHOTO ID="FAVORITE_PLACE"></PHOTO><PHOTO ID="AUTONOMY"><ENTRY><FILENAME>IMG90019.JPG</FILENAME><DATE>20170324</DATE><TIME>011839</TIME></ENTRY><ENTRY><FILENAME>TP000102.JPG</FILENAME><DATE>20000102</DATE><TIME>041620</TIME></ENTRY></PHOTO></PHOTOLIST>